filmbuff/__init__.py
filmbuff/__main__.py
filmbuff/arguments.py
filmbuff/extdata.py
filmbuff/information.py
filmbuff/interface.py
filmbuff/metadata.py
filmbuff/tablequery.py
filmbuff/resources/__init__.py
filmbuff/resources/filmbuff.desktop
filmbuff/resources/help.md
filmbuff/resources/tmdb_logo.svg
filmbuff-1.0.0.dist-info/LICENSE
filmbuff-1.0.0.dist-info/METADATA
filmbuff-1.0.0.dist-info/WHEEL
filmbuff-1.0.0.dist-info/entry_points.txt
filmbuff-1.0.0.dist-info/top_level.txt
filmbuff-1.0.0.dist-info/RECORD
