Metadata-Version: 2.1
Name: filmbuff
Version: 1.0.0
Summary: A GUI application for creating and managing local film information databases.
Home-page: https://gitlab.com/emerac/filmbuff
Author: emerac
Author-email: 
License: GPLv3
Keywords: python,GUI,film,films,movie,movies,information,database,databases,front-end,front-ends,sqlite
Platform: UNKNOWN
Classifier: License :: OSI Approved :: GNU General Public License v3 or later (GPLv3+)
Classifier: Programming Language :: Python :: 3 :: Only
Classifier: Programming Language :: Python :: 3.9
Classifier: Programming Language :: Python :: 3.8
Classifier: Intended Audience :: End Users/Desktop
Classifier: Operating System :: POSIX :: Linux
Classifier: Topic :: Database :: Front-Ends
Classifier: Development Status :: 5 - Production/Stable
Requires-Python: >=3.8
License-File: LICENSE
Requires-Dist: PyQt5 (>=5.15.4)
Requires-Dist: requests (>=2.25.1)
Requires-Dist: send2trash (>=1.7.1)
